proxy_connector/__init__.py
proxy_connector/connection_config.py
proxy_connector/local_client.py
proxy_connector/remote_proxy.py
proxy_connector/utils.py
proxy_connector-0.1.1.dist-info/METADATA
proxy_connector-0.1.1.dist-info/WHEEL
proxy_connector-0.1.1.dist-info/RECORD
