Metadata-Version: 2.3
Name: proxy-connector
Version: 0.1.1
Summary: 
Author: AndreyLinyushinIU
Author-email: AndreyLinyushin@yandex.ru
Requires-Python: >=3.12
Classifier: Programming Language :: Python :: 3
Classifier: Programming Language :: Python :: 3.12
Classifier: Programming Language :: Python :: 3.13
Requires-Dist: standarted-logger (>=0.0.6,<0.0.7)
